kash/__init__.py
kash/py.typed
kash/docs/concepts/__init__.py
kash/kits/__init__.py
kash/kits/docs/__init__.py
kash/kits/docs/__main__.py
kash/kits/docs/actions/__init__.py
kash/kits/docs/actions/concepts/__init__.py
kash/kits/docs/actions/concepts/add_list_of_concepts.py
kash/kits/docs/actions/concepts/find_near_duplicates.py
kash/kits/docs/actions/concepts/identify_concepts.py
kash/kits/docs/actions/concepts/normalize_concept_list.py
kash/kits/docs/actions/concepts/save_concepts.py
kash/kits/docs/actions/concepts/wiki_enrich_concepts.py
kash/kits/docs/actions/publish/__init__.py
kash/kits/docs/actions/publish/s3_upload.py
kash/kits/docs/actions/text/__init__.py
kash/kits/docs/actions/text/add_description.py
kash/kits/docs/actions/text/add_summary_bullets.py
kash/kits/docs/actions/text/analyze_claims.py
kash/kits/docs/actions/text/analyze_full.py
kash/kits/docs/actions/text/break_into_paragraphs.py
kash/kits/docs/actions/text/browser_fetch.py
kash/kits/docs/actions/text/chunk_paragraphs.py
kash/kits/docs/actions/text/create_docx.py
kash/kits/docs/actions/text/create_pdf.py
kash/kits/docs/actions/text/describe_briefly.py
kash/kits/docs/actions/text/docx_dump_raw.py
kash/kits/docs/actions/text/docx_to_html.py
kash/kits/docs/actions/text/docx_to_md.py
kash/kits/docs/actions/text/endnotes_to_footnotes.py
kash/kits/docs/actions/text/extract_doc_links.py
kash/kits/docs/actions/text/extract_granular_claims.py
kash/kits/docs/actions/text/extract_key_claims.py
kash/kits/docs/actions/text/fact_check_paras.py
kash/kits/docs/actions/text/fetch_links.py
kash/kits/docs/actions/text/granular_claims.py
kash/kits/docs/actions/text/insert_section_headings.py
kash/kits/docs/actions/text/markdownify_doc.py
kash/kits/docs/actions/text/markdownify_doc_links.py
kash/kits/docs/actions/text/pandoc_markdownify.py
kash/kits/docs/actions/text/pdf_to_md.py
kash/kits/docs/actions/text/prettify_html.py
kash/kits/docs/actions/text/research_paras.py
kash/kits/docs/actions/text/summarize_paras.py
kash_docs-0.1.19.dist-info/METADATA
kash_docs-0.1.19.dist-info/WHEEL
kash_docs-0.1.19.dist-info/entry_points.txt
kash_docs-0.1.19.dist-info/licenses/LICENSE
kash_docs-0.1.19.dist-info/RECORD
